comlrl/__init__.py
comlrl/models/__init__.py
comlrl/models/actor_critic.py
comlrl/trainers/__init__.py
comlrl/trainers/iac.py
comlrl/trainers/maac.py
comlrl/trainers/magrpo.py
comlrl/trainers/mareinforce.py
comlrl/trainers/maremax.py
comlrl/trainers/marloo.py
comlrl/utils/__init__.py
comlrl/utils/reward_processor.py
comlrl-1.3.2.dist-info/licenses/LICENSE
comlrl-1.3.2.dist-info/METADATA
comlrl-1.3.2.dist-info/WHEEL
comlrl-1.3.2.dist-info/top_level.txt
comlrl-1.3.2.dist-info/RECORD
