Metadata-Version: 2.4
Name: comlrl
Version: 1.3.2
Summary: Open-Source Library for Cooperative Multi-LLM Reinforcement Learning
Requires-Python: >=3.10
License-File: LICENSE
Requires-Dist: datasets>=2.0.0
Requires-Dist: numpy>=1.21.0
Requires-Dist: openai>=1.0.0
Requires-Dist: packaging>=21.0
Requires-Dist: pyyaml>=6.0.1
Requires-Dist: tqdm>=4.65.0
Requires-Dist: transformers>=4.30.0
Requires-Dist: wandb>=0.15.0
Dynamic: description
Dynamic: description-content-type
Dynamic: license-file
Dynamic: requires-dist
Dynamic: requires-python
Dynamic: summary
